Metadata-Version: 2.1
Name: gym-snake-game
Version: 0.1.2
Summary: Snake game for OpenAI Gym
Home-page: https://github.com/NaLooo/Gym_Snake_Game
Author: Ming Yu
Author-email: ming.yu@alumni.stonybrook.edu
License: MIT
Keywords: ai,rl,snake
Platform: any
Classifier: License :: OSI Approved :: MIT License
Classifier: Development Status :: 3 - Alpha
Classifier: Operating System :: OS Independent
Classifier: Topic :: Scientific/Engineering :: Artificial Intelligence
Classifier: Topic :: Games/Entertainment :: Arcade
Classifier: Programming Language :: Python :: 3.10
Requires-Python: >=3.0
License-File: LICENSE
